sunrice/__init__.py
sunrice/__main__.py
sunrice-1.0.4.dist-info/LICENSE
sunrice-1.0.4.dist-info/METADATA
sunrice-1.0.4.dist-info/WHEEL
sunrice-1.0.4.dist-info/entry_points.txt
sunrice-1.0.4.dist-info/top_level.txt
sunrice-1.0.4.dist-info/RECORD
