Metadata-Version: 2.1
Name: sunrice
Version: 1.0.4
Summary: Garden Lighting Controller
Home-page: https://github.com/hubpav/sunrice
Author: Pavel Hübner
Author-email: pavel.hubner@gmail.com
License: MIT
Keywords: lighting mqtt iot
Platform: any
Classifier: Development Status :: 5 - Production/Stable
Classifier: Environment :: Console
Classifier: Intended Audience :: Developers
Classifier: License :: OSI Approved :: MIT License
Classifier: Natural Language :: English
Classifier: Operating System :: OS Independent
Classifier: Programming Language :: Python :: 3
Classifier: Topic :: Utilities
Requires-Dist: astral (==1.6.1)
Requires-Dist: click (==7.0)
Requires-Dist: paho-mqtt (==1.4.0)
Requires-Dist: schedule (==0.5.0)
